Metadata-Version: 2.1
Name: BB-nlp
Version: 0.0.2
Summary: Tree Bank Map
Author: Mohab
Author-email: a.mohab148@gmail.com
Classifier: Development Status :: 1 - Planning
Classifier: Intended Audience :: Developers
Classifier: Topic :: Software Development
Classifier: License :: OSI Approved :: MIT License
Classifier: Programming Language :: Python :: 3
Classifier: Operating System :: OS Independent
